{"cameraMode":{"drawMode":0,"name":"Shaded","section":"Shading Mode"},"sceneLighting":true,"audioPlay":false,"sceneViewState":{"showFog":true,"showMaterialUpdate":false,"showSkybox":true,"showFlares":true,"showImageEffects":true,"showParticleSystems":true},"in2DMode":false,"pivot":{"x":-0.28753018379211428,"y":-5.041754722595215,"z":7.673919677734375},"rotation":{"x":0.2574300169944763,"y":0.015943007543683053,"z":-0.004247970413416624,"w":0.9661557078361511},"size":29.776554107666017,"orthographic":false}